all_libs/__init__.py
all_libs/file1.txt
all_libs/file2.txt
all_libs/file3.txt
all_libs/file4.txt
all_libs/file5.txt
yagamiioit-0.1.2.dist-info/LICENSE
yagamiioit-0.1.2.dist-info/METADATA
yagamiioit-0.1.2.dist-info/WHEEL
yagamiioit-0.1.2.dist-info/top_level.txt
yagamiioit-0.1.2.dist-info/RECORD
